tonellishanks/__init__.py
tonellishanks/tonellishanks.py
tonellishanks-0.1.1.dist-info/LICENSE
tonellishanks-0.1.1.dist-info/METADATA
tonellishanks-0.1.1.dist-info/WHEEL
tonellishanks-0.1.1.dist-info/top_level.txt
tonellishanks-0.1.1.dist-info/RECORD
