Metadata-Version: 2.1
Name: tonellishanks
Version: 0.1.1
Summary: Pure-Python implementation of the Tonelli–Shanks algorithm for calculating a square root modulo a prime.
Author: Andrei Lapets
Author-email: a@lapets.io
License: MIT
Project-URL: Repository, https://github.com/lapets/tonellishanks
Project-URL: Documentation, https://tonellishanks.readthedocs.io
Requires-Python: >=3.8
License-File: LICENSE
Provides-Extra: docs
Requires-Dist: toml~=0.10.2; extra == "docs"
Requires-Dist: sphinx~=5.0; extra == "docs"
Requires-Dist: sphinx-rtd-theme~=2.0.0; extra == "docs"
Provides-Extra: test
Requires-Dist: pytest~=7.4; python_version < "3.12" and extra == "test"
Requires-Dist: pytest~=8.2; python_version >= "3.12" and extra == "test"
Requires-Dist: pytest-cov~=4.1; python_version < "3.12" and extra == "test"
Requires-Dist: pytest-cov~=5.0; python_version >= "3.12" and extra == "test"
Provides-Extra: lint
Requires-Dist: pylint~=2.17.0; python_version < "3.12" and extra == "lint"
Requires-Dist: pylint~=3.2.0; python_version >= "3.12" and extra == "lint"
Provides-Extra: coveralls
Requires-Dist: coveralls~=4.0; extra == "coveralls"
Provides-Extra: publish
Requires-Dist: build~=0.10; extra == "publish"
Requires-Dist: twine~=4.0; extra == "publish"
